serious/__init__.py
serious/checks.py
serious/descriptors.py
serious/errors.py
serious/py.typed
serious/test_utils.py
serious/types.py
serious/utils.py
serious/validation.py
serious/dict/__init__.py
serious/dict/model.py
serious/json/__init__.py
serious/json/checks.py
serious/json/errors.py
serious/json/model.py
serious/json/utils.py
serious/serialization/__init__.py
serious/serialization/check_immutable.py
serious/serialization/context.py
serious/serialization/field_serializers.py
serious/serialization/key_mapper.py
serious/serialization/model.py
serious/serialization/serializer.py
serious-1.6.2.dist-info/LICENSE
serious-1.6.2.dist-info/METADATA
serious-1.6.2.dist-info/WHEEL
serious-1.6.2.dist-info/top_level.txt
serious-1.6.2.dist-info/RECORD
