Metadata-Version: 2.1
Name: serious
Version: 1.6.2
Summary: Easily serialize dataclasses to and from JSON
Home-page: https://github.com/mdrachuk/serious
Author: mdrachuk
Author-email: misha@drach.uk
License: MIT
Project-URL: Pipelines, https://dev.azure.com/misha-drachuk/serious
Project-URL: Source, https://github.com/mdrachuk/serious/
Project-URL: Issues, https://github.com/mdrachuk/serious/issues
Keywords: dataclasses json serialization
Classifier: Intended Audience :: Developers
Classifier: Topic :: Utilities
Classifier: Development Status :: 3 - Alpha
Classifier: License :: OSI Approved :: MIT License
Classifier: Natural Language :: English
Classifier: Operating System :: MacOS :: MacOS X
Classifier: Operating System :: POSIX
Classifier: Operating System :: POSIX :: BSD
Classifier: Operating System :: POSIX :: Linux
Classifier: Operating System :: Microsoft :: Windows
Classifier: Programming Language :: Python
Classifier: Programming Language :: Python :: 3.7
Classifier: Programming Language :: Python :: Implementation :: CPython
Classifier: Typing :: Typed
Requires-Python: >=3.10
License-File: LICENSE
